odoo/addons/l10n_br_delivery_nfe/README.rst
odoo/addons/l10n_br_delivery_nfe/__init__.py
odoo/addons/l10n_br_delivery_nfe/__manifest__.py
odoo/addons/l10n_br_delivery_nfe/i18n/l10n_br_delivery_nfe.pot
odoo/addons/l10n_br_delivery_nfe/models/__init__.py
odoo/addons/l10n_br_delivery_nfe/models/document.py
odoo/addons/l10n_br_delivery_nfe/readme/CONFIGURE.rst
odoo/addons/l10n_br_delivery_nfe/readme/CONTRIBUTORS.rst
odoo/addons/l10n_br_delivery_nfe/readme/DESCRIPTION.rst
odoo/addons/l10n_br_delivery_nfe/readme/HISTORY.rst
odoo/addons/l10n_br_delivery_nfe/readme/INSTALL.rst
odoo/addons/l10n_br_delivery_nfe/readme/ROADMAP.rst
odoo/addons/l10n_br_delivery_nfe/readme/USAGE.rst
odoo/addons/l10n_br_delivery_nfe/static/description/icon.png
odoo/addons/l10n_br_delivery_nfe/static/description/index.html
odoo/addons/l10n_br_delivery_nfe/views/nfe_document_view.xml
odoo12_addon_l10n_br_delivery_nfe-12.0.1.0.0.99.dev4.dist-info/METADATA
odoo12_addon_l10n_br_delivery_nfe-12.0.1.0.0.99.dev4.dist-info/WHEEL
odoo12_addon_l10n_br_delivery_nfe-12.0.1.0.0.99.dev4.dist-info/top_level.txt
odoo12_addon_l10n_br_delivery_nfe-12.0.1.0.0.99.dev4.dist-info/RECORD
